<?xml version="1.0" encoding="utf-8"?>
<!DOCTYPE hibernate-mapping PUBLIC "-//Hibernate/Hibernate Mapping DTD 3.0//EN"
"http://www.hibernate.org/dtd/hibernate-mapping-3.0.dtd">
<!-- 
    Mapping file autogenerated by MyEclipse Persistence Tools
-->
<hibernate-mapping>
    <class name="s.model.Order" table="_order" catalog="st">
        <id name="oid" type="java.lang.Integer">
            <column name="oid" />
            <generator class="native" />
        </id>
        <many-to-one name="user" class="s.model.User" fetch="select">
            <column name="uid" />
        </many-to-one>
        <property name="total" type="java.lang.Double">
            <column name="total" precision="22" scale="0" />
        </property>
        <property name="realname">
            <column name="realname"/>
        </property>
        <property name="phone">
            <column name="phone"/>
        </property>
        <property name="address">
            <column name="address"/>
        </property>
        <property name="zipcode">
            <column name="zipcode"/>
        </property>
        <property name="time">
            <column name="time" length="0" />
        </property>
        <property name="state" type="java.lang.Integer">
            <column name="state" />
        </property>
        <set name="orderItems" lazy="false" cascade="all">
            <key>
                <column name="oid" />
            </key>
            <one-to-many class="s.model.OrderItem" />
        </set>
    </class>
</hibernate-mapping>
